llunar/__init__.py
llunar/__main__.py
llunar/compiler/__init__.py
llunar/compiler/cli.py
llunar/compiler/compiler.py
llunar/lexical/__init__.py
llunar/lexical/lexer.py
llunar/lexical/tokens.py
llunar/parser/__init__.py
llunar/parser/binary/__init__.py
llunar/parser/expressions/__init__.py
llunar/parser/functions/__init__.py
llunar/parser/parser.py
llunar/parser/statements/__init__.py
llunar-0.1.0.dist-info/LICENSE
llunar-0.1.0.dist-info/WHEEL
llunar-0.1.0.dist-info/METADATA
llunar-0.1.0.dist-info/RECORD
